tortoise_factory/factory.py
tortoise_factory-0.1.0.dist-info/LICENSE
tortoise_factory-0.1.0.dist-info/METADATA
tortoise_factory-0.1.0.dist-info/WHEEL
tortoise_factory-0.1.0.dist-info/RECORD
