Metadata-Version: 2.1
Name: tortoise-factory
Version: 0.1.0
Summary: Populate Tortoise Model with faker output in a factory for tests
License: MIT
Author: Sebastien Nicolet
Author-email: snicolet95@gmail.com
Requires-Python: >=3.11,<4.0
Classifier: License :: OSI Approved :: MIT License
Classifier: Programming Language :: Python :: 3
Classifier: Programming Language :: Python :: 3.11
Classifier: Programming Language :: Python :: 3.12
Requires-Dist: faker (>=28.4.1,<29.0.0)
Requires-Dist: tortoise-orm (>=0.21.6,<0.22.0)
